pyproteum/__init__.py
pyproteum/__main__.py
pyproteum/execution_reg.py
pyproteum/exemuta.py
pyproteum/mutagen.py
pyproteum/mutaview.py
pyproteum/mutaviewgui.py
pyproteum/print_visit.py
pyproteum/tcase.py
pyproteum/testnew.py
pyproteum/utiles.py
pyproteum/models/models.py
pyproteum/moperators/cccr.py
pyproteum/moperators/ccsr.py
pyproteum/moperators/crcr.py
pyproteum/moperators/myoperator.py
pyproteum/moperators/oaaa.py
pyproteum/moperators/oaan.py
pyproteum/moperators/oeap.py
pyproteum/moperators/oodl.py
pyproteum/moperators/oplist.py
pyproteum/moperators/orrn.py
pyproteum/moperators/sbrc.py
pyproteum/moperators/scrb.py
pyproteum/moperators/ssdl.py
pyproteum-0.2.dist-info/licenses/LICENSE
pyproteum-0.2.dist-info/METADATA
pyproteum-0.2.dist-info/WHEEL
pyproteum-0.2.dist-info/entry_points.txt
pyproteum-0.2.dist-info/top_level.txt
pyproteum-0.2.dist-info/RECORD
