Metadata-Version: 2.4
Name: pyproteum
Version: 0.2
Summary: A tool for mutation testing in Python. Implemented as a Python module.
Author: Delamaro
Author-email: Delamaro <delamaro@icmc.usp.br>
Requires-Python: >=3.10
License-File: LICENSE
Requires-Dist: timeout-decorator
Requires-Dist: peewee
Dynamic: author
Dynamic: license-file
Dynamic: requires-python
